aiohttp_azure_logging/__init__.py
aiohttp_azure_logging/client.py
aiohttp_azure_logging/decorators.py
aiohttp_azure_logging/handler.py
aiohttp_azure_logging/middleware.py
aiohttp_azure_logging/setup.py
aiohttp_azure_logging/utils.py
aiohttp_azure_logging-1.1.9.dist-info/METADATA
aiohttp_azure_logging-1.1.9.dist-info/RECORD
aiohttp_azure_logging-1.1.9.dist-info/WHEEL
aiohttp_azure_logging-1.1.9.dist-info/top_level.txt
